{"grade": "5", "subject": "Reading", "test_date": "2023-07-05 00:00:00", "score": 61, "student_id": 2034}
{"grade": "7", "subject": "Math", "test_date": "2023-06-16 00:00:00", "score": 47, "student_id": 4839}
{"grade": "8", "subject": "Reading", "test_date": "2023-11-27 00:00:00", "score": 87, "student_id": 7100}
{"grade": "4", "subject": "Science", "test_date": "2023-01-26 00:00:00", "score": 59, "student_id": 7896}
{"grade": "4", "subject": "Science", "test_date": "2023-06-15 00:00:00", "score": 91, "student_id": 2079}
{"grade": "7", "subject": "Reading", "test_date": "2023-07-20 00:00:00", "score": 97, "student_id": 3633}
